AUTHORS.txt
COPYING.txt
MANIFEST.in
README.txt
TODO.txt
ez_setup.py
hgimportsvn.py
hgpullsvn.py
hgpushsvn.py
setup.cfg
setup.py
hgsvn/__init__.py
hgsvn/common.py
hgsvn/errors.py
hgsvn/hgclient.py
hgsvn/shell.py
hgsvn/svnclient.py
hgsvn/ui.py
hgsvn.egg-info/PKG-INFO
hgsvn.egg-info/SOURCES.txt
hgsvn.egg-info/dependency_links.txt
hgsvn.egg-info/entry_points.txt
hgsvn.egg-info/requires.txt
hgsvn.egg-info/top_level.txt
hgsvn/run/__init__.py
hgsvn/run/common.py
hgsvn/run/hgimportsvn.py
hgsvn/run/hgpullsvn.py
hgsvn/run/hgpushsvn.py
hgsvn/unittests/__init__.py
hgsvn/unittests/_test.py
hgsvn/unittests/test_client_utf.py
hgsvn/unittests/test_common.py
hgsvn/unittests/test_hgclient.py
hgsvn/unittests/test_hgclient_base.py
hgsvn/unittests/test_svnclient.py
man1/hgimportsvn.1
man1/hgpullsvn.1
man1/hgpushsvn.1