Metadata-Version: 1.1
Name: hgsvn
Version: 0.5.1
Summary: A set of scripts to work locally on Subversion checkouts using Mercurial
Home-page: http://bitbucket.org/alexrayne/hgsvn
Author: alexrayne
Author-email: alexraynepe196@gmail.com
License: GNU GPL
Platform: UNKNOWN
Classifier: Development Status :: 4 - Beta
Classifier: Environment :: Console
Classifier: Intended Audience :: Developers
Classifier: License :: OSI Approved :: GNU General Public License (GPL)
Classifier: Natural Language :: English
Classifier: Operating System :: OS Independent
Classifier: Programming Language :: Python
Classifier: Programming Language :: Python :: 2.7
Classifier: Programming Language :: Python :: 3.4
Classifier: Topic :: Software Development :: Version Control
